parts/__init__.py
parts/parts.py
parts-4.0.0.dist-info/licenses/LICENSE
parts-4.0.0.dist-info/METADATA
parts-4.0.0.dist-info/WHEEL
parts-4.0.0.dist-info/top_level.txt
parts-4.0.0.dist-info/RECORD
