Metadata-Version: 2.4
Name: parts
Version: 4.0.0
Summary: Minimal library that enables partitioning of iterable collections in a concise manner.
Author: Andrei Lapets
Author-email: a@lapets.io
License-Expression: MIT
Project-URL: Repository, https://github.com/lapets/parts
Project-URL: Documentation, https://parts.readthedocs.io
Requires-Python: >=3.9
License-File: LICENSE
Provides-Extra: docs
Requires-Dist: toml~=0.10.2; extra == "docs"
Requires-Dist: sphinx~=7.4; extra == "docs"
Requires-Dist: sphinx-rtd-theme~=3.0; extra == "docs"
Requires-Dist: sphinx-autodoc-typehints~=2.3; extra == "docs"
Provides-Extra: test
Requires-Dist: pytest~=7.4; python_version < "3.12" and extra == "test"
Requires-Dist: pytest~=8.4; python_version >= "3.12" and extra == "test"
Requires-Dist: pytest-cov~=4.1; python_version < "3.12" and extra == "test"
Requires-Dist: pytest-cov~=7.0; python_version >= "3.12" and extra == "test"
Provides-Extra: lint
Requires-Dist: pylint~=2.17.0; python_version < "3.12" and extra == "lint"
Requires-Dist: pylint~=3.3.0; python_version >= "3.12" and extra == "lint"
Provides-Extra: coveralls
Requires-Dist: coveralls~=4.0; extra == "coveralls"
Provides-Extra: publish
Requires-Dist: build~=0.10; extra == "publish"
Requires-Dist: twine~=4.0; extra == "publish"
Dynamic: license-file
